servai_model/__init__.py
servai_model/main.py
servai_model/core/__init__.py
servai_model/core/config.py
servai_model/core/embedding.py
servai_model/core/noise.py
servai_model/core/similarity.py
servai_model/core/speaker_analysis.py
servai_model/core/vad.py
servai_model/utils/__init__.py
servai_model/utils/logger.py
servai_model/utils/utils.py
servai_model-0.1.0.dist-info/licenses/LICENSE
servai_model-0.1.0.dist-info/METADATA
servai_model-0.1.0.dist-info/WHEEL
servai_model-0.1.0.dist-info/entry_points.txt
servai_model-0.1.0.dist-info/top_level.txt
servai_model-0.1.0.dist-info/RECORD
