Metadata-Version: 2.4
Name: servai-model
Version: 0.1.0
Summary: Whisper 및 ECAPA-TDNN 기반의 실차 화자 식별 및 노이즈 보정 라이브러리
Author-email: ServAI-Hub <contact@servai-hub.io>
License: MIT
Project-URL: Homepage, https://github.com/ServAI-Hub/servai-model
Project-URL: Bug Tracker, https://github.com/ServAI-Hub/servai-model/issues
Keywords: speaker-verification,speaker-diarization,stt,whisper,ecapa-tdnn,noise-compensation
Classifier: Programming Language :: Python :: 3
Classifier: Programming Language :: Python :: 3.11
Classifier: License :: OSI Approved :: MIT License
Classifier: Operating System :: OS Independent
Classifier: Topic :: Scientific/Engineering :: Artificial Intelligence
Classifier: Topic :: Multimedia :: Sound/Audio :: Analysis
Requires-Python: <3.12,>=3.11
License-File: LICENSE
Requires-Dist: fastapi>=0.100.0
Requires-Dist: librosa>=0.11.0
Requires-Dist: ngrok>=1.4.0
Requires-Dist: noisereduce>=3.0.3
Requires-Dist: numpy<2,>=1.26
Requires-Dist: psutil>=7.1.3
Requires-Dist: pyngrok>=7.4.1
Requires-Dist: python-multipart>=0.0.20
Requires-Dist: requests>=2.32.5
Requires-Dist: scipy>=1.16.3
Requires-Dist: setuptools>=80.9.0
Requires-Dist: soundfile>=0.13.1
Requires-Dist: speechbrain>=1.0.0
Requires-Dist: torch==2.3.1
Requires-Dist: torchaudio==2.3.1
Requires-Dist: huggingface-hub<0.20
Requires-Dist: uvicorn>=0.38.0
Requires-Dist: webrtcvad>=2.0.10
Requires-Dist: whisper-mps>=0.0.10
Requires-Dist: openai-whisper>=20250625
Dynamic: license-file
